meanfi/__init__.py
meanfi/_version.py
meanfi/mf.py
meanfi/model.py
meanfi/observables.py
meanfi/solvers.py
meanfi/kwant_helper/__init__.py
meanfi/kwant_helper/kwant_examples.py
meanfi/kwant_helper/utils.py
meanfi/params/__init__.py
meanfi/params/param_transforms.py
meanfi/params/rparams.py
meanfi/tb/__init__.py
meanfi/tb/tb.py
meanfi/tb/transforms.py
meanfi/tb/utils.py
meanfi/tests/test_graphene.py
meanfi/tests/test_hat.py
meanfi/tests/test_hubbard.py
meanfi/tests/test_params.py
meanfi/tests/test_tb.py
meanfi/tests/test_zero_hint.py
meanfi-1.0.0.dist-info/METADATA
meanfi-1.0.0.dist-info/WHEEL
meanfi-1.0.0.dist-info/licenses/AUTHORS.md
meanfi-1.0.0.dist-info/licenses/LICENSE
meanfi-1.0.0.dist-info/RECORD
