Metadata-Version: 2.3
Name: meanfi
Version: 1.0.0
Summary: Package to perform self-consistent mean-field calculations on tight-binding systems
Project-URL: Documentation, https://meanfi.readthedocs.io/en/latest/
Project-URL: Repository, https://gitlab.kwant-project.org/qt/meanfi
Project-URL: Bug Tracker, https://gitlab.kwant-project.org/qt/meanfi/-/issues
Author: MeanFi developers
License-File: AUTHORS.md
License-File: LICENSE
Classifier: Development Status :: 4 - Beta
Classifier: Intended Audience :: Science/Research
Classifier: License :: OSI Approved :: BSD License
Classifier: Programming Language :: Python :: 3.10
Classifier: Programming Language :: Python :: 3.11
Classifier: Programming Language :: Python :: 3.12
Requires-Python: >=3.10
Requires-Dist: kwant>=1.4
Requires-Dist: numpy>=1.23
Requires-Dist: packaging>=22.0
Requires-Dist: scipy>=1.9
